tests/__init__.py
tests/test_browser.py
tests/test_requests.py
tests/test_trawlit.py
trawler/__init__.py
trawler/settings.py
trawler/trawl.py
trawler/browsers/__init__.py
trawler/browsers/base.py
trawler/browsers/bing.py
trawler/browsers/exceptions.py
trawler/browsers/stackoverflow.py
trawler/browsers/utils.py
trawler/browsers/wordpress.py
trawler-1.3.6.dist-info/DESCRIPTION.rst
trawler-1.3.6.dist-info/METADATA
trawler-1.3.6.dist-info/RECORD
trawler-1.3.6.dist-info/WHEEL
trawler-1.3.6.dist-info/metadata.json
trawler-1.3.6.dist-info/top_level.txt
